ledger/__init__.py
ledger/_version.py
ledger/py.typed
ledger/core/__init__.py
ledger/core/base_middleware.py
ledger/core/buffer.py
ledger/core/client.py
ledger/core/config.py
ledger/core/flusher.py
ledger/core/http_client.py
ledger/core/rate_limiter.py
ledger/core/settings.py
ledger/core/url_processor.py
ledger/core/validator.py
ledger/integrations/__init__.py
ledger/integrations/django.py
ledger/integrations/fastapi.py
ledger/integrations/flask.py
ledger_sdk-1.2.2.dist-info/licenses/LICENSE
ledger_sdk-1.2.2.dist-info/METADATA
ledger_sdk-1.2.2.dist-info/WHEEL
ledger_sdk-1.2.2.dist-info/top_level.txt
ledger_sdk-1.2.2.dist-info/RECORD
