Metadata-Version: 2.4
Name: ledger-sdk
Version: 1.2.2
Summary: Production-ready observability SDK for Python web applications with FastAPI, Django, and Flask integrations
Author-email: Ledger Team <sdk@ledger.example.com>
License: MIT
Project-URL: Homepage, https://ledger.example.com
Project-URL: Documentation, https://docs.ledger.example.com
Project-URL: Repository, https://github.com/JakubTuta/ledger-sdk
Project-URL: Changelog, https://github.com/JakubTuta/ledger-sdk/blob/main/CHANGELOG.md
Project-URL: Bug Tracker, https://github.com/JakubTuta/ledger-sdk/issues
Keywords: logging,observability,monitoring,fastapi,django,flask,async,telemetry,apm
Classifier: Development Status :: 5 - Production/Stable
Classifier: Intended Audience :: Developers
Classifier: License :: OSI Approved :: MIT License
Classifier: Programming Language :: Python :: 3
Classifier: Programming Language :: Python :: 3.10
Classifier: Programming Language :: Python :: 3.11
Classifier: Programming Language :: Python :: 3.12
Classifier: Framework :: FastAPI
Classifier: Framework :: Django
Classifier: Framework :: Flask
Classifier: Framework :: AsyncIO
Classifier: Topic :: Software Development :: Libraries :: Python Modules
Classifier: Topic :: System :: Logging
Classifier: Topic :: System :: Monitoring
Classifier: Typing :: Typed
Requires-Python: >=3.10
License-File: LICENSE
Requires-Dist: httpx>=0.25.0
Requires-Dist: pydantic>=2.0.0
Requires-Dist: pydantic-settings>=2.0.0
Provides-Extra: fastapi
Requires-Dist: fastapi>=0.104.0; extra == "fastapi"
Requires-Dist: starlette>=0.27.0; extra == "fastapi"
Provides-Extra: flask
Requires-Dist: flask>=2.3.0; extra == "flask"
Provides-Extra: django
Requires-Dist: django>=4.2.0; extra == "django"
Provides-Extra: all
Requires-Dist: ledger-sdk[django,fastapi,flask]; extra == "all"
Provides-Extra: dev
Requires-Dist: pytest>=7.4.0; extra == "dev"
Requires-Dist: pytest-asyncio>=0.21.0; extra == "dev"
Requires-Dist: pytest-cov>=4.1.0; extra == "dev"
Requires-Dist: pytest-mock>=3.11.0; extra == "dev"
Requires-Dist: black>=23.0.0; extra == "dev"
Requires-Dist: ruff>=0.1.0; extra == "dev"
Requires-Dist: mypy>=1.5.0; extra == "dev"
Requires-Dist: httpx[http2]>=0.25.0; extra == "dev"
Requires-Dist: fastapi>=0.104.0; extra == "dev"
Requires-Dist: starlette>=0.27.0; extra == "dev"
Requires-Dist: uvicorn>=0.24.0; extra == "dev"
Requires-Dist: django>=4.2.0; extra == "dev"
Requires-Dist: flask>=2.3.0; extra == "dev"
Dynamic: license-file
